odoo10_addon_l10n_ch_dta-10.0.1.0.2-py2.7-nspkg.pth
odoo/addons/l10n_ch_dta/README.rst
odoo/addons/l10n_ch_dta/__init__.py
odoo/addons/l10n_ch_dta/__manifest__.py
odoo/addons/l10n_ch_dta/bank_view.xml
odoo/addons/l10n_ch_dta/post_install.py
odoo/addons/l10n_ch_dta/data/account_payment_method.xml
odoo/addons/l10n_ch_dta/demo/dta_demo.xml
odoo/addons/l10n_ch_dta/i18n/am.po
odoo/addons/l10n_ch_dta/i18n/ar.po
odoo/addons/l10n_ch_dta/i18n/bg.po
odoo/addons/l10n_ch_dta/i18n/bs.po
odoo/addons/l10n_ch_dta/i18n/ca.po
odoo/addons/l10n_ch_dta/i18n/cs.po
odoo/addons/l10n_ch_dta/i18n/da.po
odoo/addons/l10n_ch_dta/i18n/de.po
odoo/addons/l10n_ch_dta/i18n/el_GR.po
odoo/addons/l10n_ch_dta/i18n/en_GB.po
odoo/addons/l10n_ch_dta/i18n/es.po
odoo/addons/l10n_ch_dta/i18n/es_AR.po
odoo/addons/l10n_ch_dta/i18n/es_CO.po
odoo/addons/l10n_ch_dta/i18n/es_CR.po
odoo/addons/l10n_ch_dta/i18n/es_DO.po
odoo/addons/l10n_ch_dta/i18n/es_EC.po
odoo/addons/l10n_ch_dta/i18n/es_ES.po
odoo/addons/l10n_ch_dta/i18n/es_MX.po
odoo/addons/l10n_ch_dta/i18n/es_PE.po
odoo/addons/l10n_ch_dta/i18n/es_VE.po
odoo/addons/l10n_ch_dta/i18n/et.po
odoo/addons/l10n_ch_dta/i18n/eu.po
odoo/addons/l10n_ch_dta/i18n/fa.po
odoo/addons/l10n_ch_dta/i18n/fi.po
odoo/addons/l10n_ch_dta/i18n/fr.po
odoo/addons/l10n_ch_dta/i18n/fr_CH.po
odoo/addons/l10n_ch_dta/i18n/gl.po
odoo/addons/l10n_ch_dta/i18n/gl_ES.po
odoo/addons/l10n_ch_dta/i18n/he.po
odoo/addons/l10n_ch_dta/i18n/hr.po
odoo/addons/l10n_ch_dta/i18n/hr_HR.po
odoo/addons/l10n_ch_dta/i18n/hu.po
odoo/addons/l10n_ch_dta/i18n/id.po
odoo/addons/l10n_ch_dta/i18n/it.po
odoo/addons/l10n_ch_dta/i18n/ja.po
odoo/addons/l10n_ch_dta/i18n/ko.po
odoo/addons/l10n_ch_dta/i18n/l10n_ch_dta.pot
odoo/addons/l10n_ch_dta/i18n/lt.po
odoo/addons/l10n_ch_dta/i18n/lv.po
odoo/addons/l10n_ch_dta/i18n/mk.po
odoo/addons/l10n_ch_dta/i18n/mn.po
odoo/addons/l10n_ch_dta/i18n/nb.po
odoo/addons/l10n_ch_dta/i18n/nb_NO.po
odoo/addons/l10n_ch_dta/i18n/nl.po
odoo10_addon_l10n_ch_dta-10.0.1.0.2.dist-info/DESCRIPTION.rst
odoo10_addon_l10n_ch_dta-10.0.1.0.2.dist-info/METADATA
odoo10_addon_l10n_ch_dta-10.0.1.0.2.dist-info/RECORD
odoo10_addon_l10n_ch_dta-10.0.1.0.2.dist-info/WHEEL
odoo10_addon_l10n_ch_dta-10.0.1.0.2.dist-info/metadata.json
odoo10_addon_l10n_ch_dta-10.0.1.0.2.dist-info/namespace_packages.txt
odoo10_addon_l10n_ch_dta-10.0.1.0.2.dist-info/top_level.txt
