Metadata-Version: 2.0
Name: odoo10-addon-l10n-ch-dta
Version: 10.0.1.0.2
Summary: Electronic payment file for Swiss bank (DTA)
Home-page: http://www.camptocamp.com
Author: Camptocamp,Odoo Community Association (OCA)
Author-email: support@odoo-community.org
License: AGPL-3
Platform: UNKNOWN
Classifier: Programming Language :: Python
Classifier: Framework :: Odoo
Classifier: License :: OSI Approved :: GNU Affero General Public License v3
Requires-Python: ~=2.7
Requires-Dist: odoo (<10.1dev,>=10.0)
Requires-Dist: odoo10-addon-account-payment-order
Requires-Dist: odoo10-addon-l10n-ch-base-bank
